utils_ag/__init__.py
utils_ag/filesystem.py
utils_ag/first.py
utils_ag/io.py
utils_ag-0.0.16.dist-info/LICENSE
utils_ag-0.0.16.dist-info/METADATA
utils_ag-0.0.16.dist-info/WHEEL
utils_ag-0.0.16.dist-info/top_level.txt
utils_ag-0.0.16.dist-info/RECORD
